sqla_inspect/__init__.py
sqla_inspect/ascii.py
sqla_inspect/base.py
sqla_inspect/csv.py
sqla_inspect/excel.py
sqla_inspect/export.py
sqla_inspect/ods.py
sqla_inspect/py3o.py
sqla_inspect/py3o_tmpl.py
sqla_inspect/.ruff_cache/.gitignore
sqla_inspect/.ruff_cache/CACHEDIR.TAG
sqla_inspect/.ruff_cache/0.13.1/10725424277064709988
sqla_inspect/.ruff_cache/0.13.1/11988752199463328367
sqla_inspect/__pycache__/__init__.cpython-311.pyc
sqla_inspect/__pycache__/__init__.cpython-37-pytest-6.2.1.pyc
sqla_inspect/__pycache__/__init__.cpython-37.pyc
sqla_inspect/__pycache__/__init__.cpython-38.pyc
sqla_inspect/__pycache__/__init__.cpython-39-pytest-6.2.5.pyc
sqla_inspect/__pycache__/__init__.cpython-39.pyc
sqla_inspect/__pycache__/ascii.cpython-311.pyc
sqla_inspect/__pycache__/ascii.cpython-37.pyc
sqla_inspect/__pycache__/ascii.cpython-38.pyc
sqla_inspect/__pycache__/ascii.cpython-39-pytest-6.2.5.pyc
sqla_inspect/__pycache__/ascii.cpython-39.pyc
sqla_inspect/__pycache__/base.cpython-311.pyc
sqla_inspect/__pycache__/base.cpython-37-pytest-6.2.1.pyc
sqla_inspect/__pycache__/base.cpython-37.pyc
sqla_inspect/__pycache__/base.cpython-38.pyc
sqla_inspect/__pycache__/base.cpython-39-pytest-6.2.5.pyc
sqla_inspect/__pycache__/base.cpython-39.pyc
sqla_inspect/__pycache__/csv.cpython-311.pyc
sqla_inspect/__pycache__/csv.cpython-37-pytest-6.2.1.pyc
sqla_inspect/__pycache__/csv.cpython-37.pyc
sqla_inspect/__pycache__/csv.cpython-38.pyc
sqla_inspect/__pycache__/csv.cpython-39-pytest-6.2.5.pyc
sqla_inspect/__pycache__/csv.cpython-39.pyc
sqla_inspect/__pycache__/excel.cpython-311.pyc
sqla_inspect/__pycache__/excel.cpython-37-pytest-6.2.1.pyc
sqla_inspect/__pycache__/excel.cpython-37.pyc
sqla_inspect/__pycache__/excel.cpython-38.pyc
sqla_inspect/__pycache__/excel.cpython-39-pytest-6.2.5.pyc
sqla_inspect/__pycache__/excel.cpython-39.pyc
sqla_inspect/__pycache__/export.cpython-311.pyc
sqla_inspect/__pycache__/export.cpython-37-pytest-6.2.1.pyc
sqla_inspect/__pycache__/export.cpython-37.pyc
sqla_inspect-0.9.1.dist-info/licenses/LICENSE.txt
sqla_inspect-0.9.1.dist-info/METADATA
sqla_inspect-0.9.1.dist-info/WHEEL
sqla_inspect-0.9.1.dist-info/top_level.txt
sqla_inspect-0.9.1.dist-info/RECORD
